CHANGES.rst
DESCRIPTION.rst
LICENSE.rst
MANIFEST.in
README.rst
pyproject.toml
setup.cfg
setup.py
conf/__init__.py
conf/confpetsc.py
conf/confslepc.py
conf/cyautodoc.py
conf/cythonize.py
conf/cythonize.sh
demo/ex1.py
demo/ex10.py
demo/ex11.py
demo/ex12.py
demo/ex13.py
demo/ex14.py
demo/ex2.py
demo/ex3.py
demo/ex4.py
demo/ex5.py
demo/ex6.py
demo/ex7.py
demo/ex8.py
demo/ex9.py
demo/makefile
docs/source/Makefile
docs/source/apidoc.py
docs/source/changes.rst
docs/source/citing.rst
docs/source/conf.py
docs/source/index.rst
docs/source/install.rst
docs/source/links.txt
docs/source/overview.rst
docs/source/reference.rst
docs/source/tutorial.rst
docs/source/_templates/layout.html
docs/source/_templates/autosummary/class.rst
docs/source/_templates/autosummary/module.rst
docs/source/demo/demo.rst
docs/source/demo/ex1.py
docs/source/demo/ex1.rst
docs/source/demo/ex10.py
docs/source/demo/ex10.rst
docs/source/demo/ex11.py
docs/source/demo/ex11.rst
docs/source/demo/ex12.py
docs/source/demo/ex12.rst
docs/source/demo/ex13.py
docs/source/demo/ex13.rst
docs/source/demo/ex14.py
docs/source/demo/ex14.rst
docs/source/demo/ex2.py
docs/source/demo/ex2.rst
docs/source/demo/ex3.py
docs/source/demo/ex3.rst
docs/source/demo/ex4.py
docs/source/demo/ex4.rst
docs/source/demo/ex5.py
docs/source/demo/ex5.rst
docs/source/demo/ex6.py
docs/source/demo/ex6.rst
docs/source/demo/ex7.py
docs/source/demo/ex7.rst
docs/source/demo/ex8.py
docs/source/demo/ex8.rst
docs/source/demo/ex9.py
docs/source/demo/ex9.rst
docs/source/reference/slepc4py.SLEPc.BV.MatMultType.rst
docs/source/reference/slepc4py.SLEPc.BV.OrthogBlockType.rst
docs/source/reference/slepc4py.SLEPc.BV.OrthogRefineType.rst
docs/source/reference/slepc4py.SLEPc.BV.OrthogType.rst
docs/source/reference/slepc4py.SLEPc.BV.SVDMethod.rst
docs/source/reference/slepc4py.SLEPc.BV.Type.rst
docs/source/reference/slepc4py.SLEPc.BV.rst
docs/source/reference/slepc4py.SLEPc.CURRENT.rst
docs/source/reference/slepc4py.SLEPc.DECIDE.rst
src/slepc4py.egg-info/PKG-INFO
src/slepc4py.egg-info/SOURCES.txt
src/slepc4py.egg-info/dependency_links.txt
src/slepc4py.egg-info/not-zip-safe
src/slepc4py.egg-info/requires.txt
src/slepc4py.egg-info/top_level.txt
