Metadata-Version: 2.4
Name: slepc4py
Version: 3.24.2
Summary: SLEPc for Python
Home-page: https://gitlab.com/slepc/slepc
Download-URL: https://pypi.io/packages/source/s/slepc4py/slepc4py-3.24.2.tar.gz
Author: Lisandro Dalcin
Author-email: dalcinl@gmail.com
Maintainer: SLEPc Team
Maintainer-email: slepc-maint@upv.es
License: BSD-2-Clause
Keywords: scientific computing,parallel computing,MPI,SLEPc,PETSc
Platform: POSIX
Platform: Linux
Platform: macOS
Platform: FreeBSD
Classifier: Operating System :: POSIX
Classifier: Intended Audience :: Developers
Classifier: Intended Audience :: Science/Research
Classifier: Programming Language :: C
Classifier: Programming Language :: C++
Classifier: Programming Language :: Cython
Classifier: Programming Language :: Python
Classifier: Programming Language :: Python :: 3
Classifier: Programming Language :: Python :: Implementation :: CPython
Classifier: Topic :: Scientific/Engineering
Classifier: Topic :: Software Development :: Libraries :: Python Modules
Classifier: Development Status :: 5 - Production/Stable
Requires: numpy
License-File: LICENSE.rst
Requires-Dist: numpy
Requires-Dist: petsc4py<3.25,>=3.24
Dynamic: author
Dynamic: author-email
Dynamic: classifier
Dynamic: description
Dynamic: description-content-type
Dynamic: download-url
Dynamic: home-page
Dynamic: keywords
Dynamic: license
Dynamic: license-file
Dynamic: maintainer
Dynamic: maintainer-email
Dynamic: platform
Dynamic: requires
Dynamic: requires-dist
Dynamic: summary
